strym/DBC_Read_Tools.py
strym/README.md
strym/TODO.todo
strym/__init__.py
strym/config.py
strym/dashboard.py
strym/meta.py
strym/phasespace.py
strym/strym.py
strym/strymmap.py
strym/strymread.py
strym/tools.py
strym/version
strym/dbc/honda_pilot_2017.dbc
strym/dbc/nissan_rogue_2021.dbc
strym/dbc/toyota_rav4_2019.dbc
strym/dbc/toyota_rav4_2020.dbc
strym/dbc/toyota_rav4_2021.dbc
strym/dbc/toyota_rav4_hybrid.dbc
strym/multimode/__init__.py
strym/multimode/platoons.py
strym/utils/__init__.py
strym/utils/log.py
strym_lite-0.4.18.dist-info/LICENSE
strym_lite-0.4.18.dist-info/METADATA
strym_lite-0.4.18.dist-info/WHEEL
strym_lite-0.4.18.dist-info/top_level.txt
strym_lite-0.4.18.dist-info/RECORD
