Metadata-Version: 2.1
Name: strym-lite
Version: 0.4.18
Summary: A real time CAN data logging and visualization tool to work with USB-CAN Interface.
Home-page: https://github.com/jmscslgroup/strym
Author: Rahul Bhadani
Author-email: rahulbhadani@email.arizona.edu
License: UNKNOWN
Keywords: candata,can,autonomous vehicle,ACC,adaptive cruise control,USB,Panda,Traffic,Transportation,visualization
Platform: UNKNOWN
Classifier: Programming Language :: Python :: 3
Classifier: Framework :: AsyncIO
Classifier: Topic :: Communications
Classifier: Topic :: Scientific/Engineering :: Visualization
Classifier: License :: OSI Approved :: MIT License
Requires-Dist: pandas
Requires-Dist: setuptools
Requires-Dist: setuptools-scm
Requires-Dist: importlib-resources
Requires-Dist: importlib-metadata
Requires-Dist: ipykernel
Requires-Dist: numpy (~=1.19.2)
Requires-Dist: matplotlib (>=3.3.1)
Requires-Dist: cantools (>=32.20.1)
Requires-Dist: libusb1 (>=1.7.1)
Requires-Dist: pyserial (>=3.4)
Requires-Dist: ipython
Requires-Dist: bitstring (>=3.1.6)
Requires-Dist: python-dotenv
Requires-Dist: vin-parser
Requires-Dist: ffmpeg-python
Requires-Dist: kaleido
Requires-Dist: urllib3 (==1.24.2)
Requires-Dist: yolk3k
